[1,["16c44fe30@6c48a"],["_textureSource"],["cc.SpriteFrame"],0,[[[{"name":"bi_cloud_c","rect":{"x":282,"y":527,"width":331,"height":86},"offset":{"x":0,"y":5.5},"originalSize":{"width":331,"height":107},"rotated":false,"capInsets":[0,0,0,0],"packable":true,"pixelsToUnit":100,"pivot":{"x":0.5,"y":0.5},"meshType":0}],[0],0,[0],[0],[0]],[[{"name":"tw_button","rect":{"x":3,"y":166,"width":502,"height":175},"offset":{"x":-2,"y":0.5},"originalSize":{"width":522,"height":176},"rotated":true,"capInsets":[0,0,0,0],"packable":true,"pixelsToUnit":100,"pivot":{"x":0.5,"y":0.5},"meshType":0}],[0],0,[0],[0],[0]],[[{"name":"sw_on_bg","rect":{"x":410,"y":347,"width":37,"height":37},"offset":{"x":-1,"y":1},"originalSize":{"width":85,"height":65},"rotated":false,"capInsets":[0,0,0,0],"packable":true,"pixelsToUnit":100,"pivot":{"x":0.5,"y":0.5},"meshType":0}],[0],0,[0],[0],[0]],[[{"name":"ib_bar_a_mask","rect":{"x":453,"y":411,"width":97,"height":97},"offset":{"x":-4.5,"y":0},"originalSize":{"width":106,"height":97},"rotated":false,"capInsets":[0,0,0,0],"packable":true,"pixelsToUnit":100,"pivot":{"x":0.5,"y":0.5},"meshType":0}],[0],0,[0],[0],[0]],[[{"name":"ui_waybar","rect":{"x":3,"y":674,"width":81,"height":646},"offset":{"x":0,"y":-4.5},"originalSize":{"width":81,"height":687},"rotated":true,"capInsets":[0,0,0,0],"packable":true,"pixelsToUnit":100,"pivot":{"x":0.5,"y":0.5},"meshType":0}],[0],0,[0],[0],[0]],[[{"name":"ib_bar_a","rect":{"x":790,"y":3,"width":752,"height":151},"offset":{"x":0,"y":0},"originalSize":{"width":752,"height":151},"rotated":true,"capInsets":[0,0,0,0],"packable":true,"pixelsToUnit":100,"pivot":{"x":0.5,"y":0.5},"meshType":0}],[0],0,[0],[0],[0]],[[{"name":"bi_cloud_e","rect":{"x":655,"y":625,"width":112,"height":125},"offset":{"x":0,"y":0},"originalSize":{"width":112,"height":125},"rotated":true,"capInsets":[0,0,0,0],"packable":true,"pixelsToUnit":100,"pivot":{"x":0.5,"y":0.5},"meshType":0}],[0],0,[0],[0],[0]],[[{"name":"ib_bar_c","rect":{"x":3,"y":761,"width":791,"height":137},"offset":{"x":0,"y":3},"originalSize":{"width":791,"height":143},"rotated":false,"capInsets":[0,0,0,0],"packable":true,"pixelsToUnit":100,"pivot":{"x":0.5,"y":0.5},"meshType":0}],[0],0,[0],[0],[0]],[[{"name":"bi_cloud_d","rect":{"x":184,"y":166,"width":266,"height":175},"offset":{"x":0,"y":0},"originalSize":{"width":266,"height":175},"rotated":false,"capInsets":[0,0,0,0],"packable":true,"pixelsToUnit":100,"pivot":{"x":0.5,"y":0.5},"meshType":0}],[0],0,[0],[0],[0]],[[{"name":"bns_mtp","rect":{"x":655,"y":166,"width":453,"height":114},"offset":{"x":0,"y":0},"originalSize":{"width":455,"height":114},"rotated":true,"capInsets":[0,0,0,0],"packable":true,"pixelsToUnit":100,"pivot":{"x":0.5,"y":0.5},"meshType":0}],[0],0,[0],[0],[0]],[[{"name":"bi_cloud_b","rect":{"x":282,"y":619,"width":235,"height":43},"offset":{"x":0,"y":0},"originalSize":{"width":235,"height":43},"rotated":false,"capInsets":[0,0,0,0],"packable":true,"pixelsToUnit":100,"pivot":{"x":0.5,"y":0.5},"meshType":0}],[0],0,[0],[0],[0]],[[{"name":"fs_8","rect":{"x":282,"y":347,"width":122,"height":174},"offset":{"x":0,"y":1},"originalSize":{"width":124,"height":176},"rotated":false,"capInsets":[0,0,0,0],"packable":true,"pixelsToUnit":100,"pivot":{"x":0.5,"y":0.5},"meshType":0}],[0],0,[0],[0],[0]],[[{"name":"effectLight","rect":{"x":800,"y":761,"width":159,"height":148},"offset":{"x":-0.5,"y":2},"originalSize":{"width":180,"height":168},"rotated":false,"capInsets":[0,0,0,0],"packable":true,"pixelsToUnit":100,"pivot":{"x":0.5,"y":0.5},"meshType":0}],[0],0,[0],[0],[0]],[[{"name":"sw_wallet_prize","rect":{"x":184,"y":347,"width":282,"height":92},"offset":{"x":0,"y":0},"originalSize":{"width":282,"height":92},"rotated":true,"capInsets":[0,0,0,0],"packable":true,"pixelsToUnit":100,"pivot":{"x":0.5,"y":0.5},"meshType":0}],[0],0,[0],[0],[0]],[[{"name":"bi_cloud_a","rect":{"x":796,"y":915,"width":153,"height":28},"offset":{"x":0,"y":0},"originalSize":{"width":153,"height":28},"rotated":false,"capInsets":[0,0,0,0],"packable":true,"pixelsToUnit":100,"pivot":{"x":0.5,"y":0.5},"meshType":0}],[0],0,[0],[0],[0]],[[{"name":"sw_off_bg","rect":{"x":410,"y":390,"width":37,"height":37},"offset":{"x":-1,"y":1},"originalSize":{"width":85,"height":65},"rotated":false,"capInsets":[0,0,0,0],"packable":true,"pixelsToUnit":100,"pivot":{"x":0.5,"y":0.5},"meshType":0}],[0],0,[0],[0],[0]],[[{"name":"bns_mtp_mask","rect":{"x":654,"y":904,"width":51,"height":89},"offset":{"x":0,"y":0},"originalSize":{"width":51,"height":89},"rotated":true,"capInsets":[0,0,0,0],"packable":true,"pixelsToUnit":100,"pivot":{"x":0.5,"y":0.5},"meshType":0}],[0],0,[0],[0],[0]],[[{"name":"sw_bg","rect":{"x":456,"y":166,"width":172,"height":239},"offset":{"x":0.5,"y":0},"originalSize":{"width":195,"height":239},"rotated":false,"capInsets":[0,0,0,0],"packable":true,"pixelsToUnit":100,"pivot":{"x":0.5,"y":0.5},"meshType":0}],[0],0,[0],[0],[0]],[[{"name":"ib_bar_b","rect":{"x":3,"y":3,"width":781,"height":157},"offset":{"x":0,"y":0},"originalSize":{"width":781,"height":157},"rotated":false,"capInsets":[0,0,0,0],"packable":true,"pixelsToUnit":100,"pivot":{"x":0.5,"y":0.5},"meshType":0}],[0],0,[0],[0],[0]],[[{"name":"bns_waybar","rect":{"x":3,"y":904,"width":63,"height":645},"offset":{"x":-1,"y":-4},"originalSize":{"width":81,"height":687},"rotated":true,"capInsets":[0,0,0,0],"packable":true,"pixelsToUnit":100,"pivot":{"x":0.5,"y":0.5},"meshType":0}],[0],0,[0],[0],[0]],[[{"name":"sw_rope","rect":{"x":749,"y":904,"width":41,"height":58},"offset":{"x":0,"y":2},"originalSize":{"width":41,"height":62},"rotated":false,"capInsets":[0,0,0,0],"packable":true,"pixelsToUnit":100,"pivot":{"x":0.5,"y":0.5},"meshType":0}],[0],0,[0],[0],[0]]]]
